numind/__init__.py
numind/api_response.py
numind/constants.py
numind/exceptions.py
numind/numind.py
numind/models/__init__.py
numind/models/api_key_response.py
numind/models/convert_request.py
numind/models/create_api_key.py
numind/models/create_markdown_project_request.py
numind/models/create_or_update_example_request.py
numind/models/create_or_update_markdown_playground_item_request.py
numind/models/create_or_update_playground_item_request.py
numind/models/create_organization_request.py
numind/models/create_project_request.py
numind/models/document_info.py
numind/models/document_response.py
numind/models/error.py
numind/models/example_response.py
numind/models/extraction_response.py
numind/models/extraction_response_deprecated.py
numind/models/file_response.py
numind/models/health_response.py
numind/models/image_info.py
numind/models/inference_example.py
numind/models/inference_status.py
numind/models/inference_validation_error.py
numind/models/information_response.py
numind/models/invalid_information.py
numind/models/invitation_response.py
numind/models/invite_member_request.py
numind/models/job_id_response.py
numind/models/job_response.py
numind/models/job_status_response.py
numind/models/markdown_playground_item_response.py
numind/models/markdown_project_response.py
numind/models/markdown_project_settings_response.py
numind/models/markdown_response.py
numind/models/member_response.py
numind/models/organization_response.py
numind/models/paginated_response_example_response.py
numind/models/paginated_response_job_response.py
numind/models/paginated_response_markdown_playground_item_response.py
numind/models/paginated_response_playground_item_response.py
numind/models/playground_item_response.py
numind/models/project_response.py
numind/models/project_response_deprecated.py
numind/models/project_settings_response.py
numind/models/project_settings_response_deprecated.py
numind/models/raw_result.py
numind/models/service_status.py
numind/models/template_request.py
numind-0.2.0.dist-info/METADATA
numind-0.2.0.dist-info/WHEEL
numind-0.2.0.dist-info/licenses/LICENSE
numind-0.2.0.dist-info/RECORD
