Metadata-Version: 2.4
Name: numind
Version: 0.2.0
Summary: SDK to interact with the NuMind models API.
Project-URL: Homepage, https://github.com/numindai/nuextract-platform-sdk
Project-URL: Repository, https://github.com/numindai/nuextract-platform-sdk.git
Project-URL: Documentation, https://github.com/numindai/nuextract-platform-sdk#documentation
Project-URL: Issues, https://github.com/numindai/nuextract-platform-sdk/issues
Author-email: Nathan Fradet <nathan@numind.ai>
License: The MIT License (MIT)
License-File: LICENSE
Keywords: artificial intelligence,deep learning,structured
Classifier: Intended Audience :: Developers
Classifier: Intended Audience :: Science/Research
Classifier: License :: OSI Approved :: MIT License
Classifier: Operating System :: OS Independent
Classifier: Programming Language :: Python
Classifier: Programming Language :: Python :: 3 :: Only
Classifier: Programming Language :: Python :: 3.9
Classifier: Programming Language :: Python :: 3.10
Classifier: Programming Language :: Python :: 3.11
Classifier: Programming Language :: Python :: 3.12
Classifier: Programming Language :: Python :: 3.13
Classifier: Topic :: Scientific/Engineering :: Artificial Intelligence
Requires-Python: >=3.9
Requires-Dist: aiohttp-retry>=2.8.3
Requires-Dist: aiohttp>=3.8.4
Requires-Dist: pydantic>=2
Requires-Dist: python-dateutil>=2.8.2
Requires-Dist: typing-extensions>=4.7.1
Requires-Dist: urllib3<3.0.0,>=2.1.0
Provides-Extra: build
Requires-Dist: openapi-generator-cli; extra == 'build'
Requires-Dist: pyyaml; extra == 'build'
Requires-Dist: toml; extra == 'build'
Requires-Dist: uv; extra == 'build'
Provides-Extra: tests
Requires-Dist: pytest-asyncio; extra == 'tests'
Requires-Dist: pytest-cov; extra == 'tests'
Requires-Dist: pytest-dependency; extra == 'tests'
Requires-Dist: pytest-rerunfailures; extra == 'tests'
